odoo10_addon_l10n_it_fatturapa_out_stamp-10.0.2.0.0-nspkg.pth
odoo/addons/l10n_it_fatturapa_out_stamp/README.rst
odoo/addons/l10n_it_fatturapa_out_stamp/__init__.py
odoo/addons/l10n_it_fatturapa_out_stamp/__manifest__.py
odoo/addons/l10n_it_fatturapa_out_stamp/i18n/l10n_it_fatturapa_out_stamp.pot
odoo/addons/l10n_it_fatturapa_out_stamp/readme/CONTRIBUTORS.rst
odoo/addons/l10n_it_fatturapa_out_stamp/readme/DESCRIPTION.rst
odoo/addons/l10n_it_fatturapa_out_stamp/static/description/icon.png
odoo/addons/l10n_it_fatturapa_out_stamp/static/description/index.html
odoo/addons/l10n_it_fatturapa_out_stamp/wizard/__init__.py
odoo/addons/l10n_it_fatturapa_out_stamp/wizard/wizard_export_fatturapa.py
odoo10_addon_l10n_it_fatturapa_out_stamp-10.0.2.0.0.dist-info/METADATA
odoo10_addon_l10n_it_fatturapa_out_stamp-10.0.2.0.0.dist-info/WHEEL
odoo10_addon_l10n_it_fatturapa_out_stamp-10.0.2.0.0.dist-info/namespace_packages.txt
odoo10_addon_l10n_it_fatturapa_out_stamp-10.0.2.0.0.dist-info/top_level.txt
odoo10_addon_l10n_it_fatturapa_out_stamp-10.0.2.0.0.dist-info/RECORD
