Metadata-Version: 2.1
Name: odoo10-addon-l10n-it-fatturapa-out-stamp
Version: 10.0.2.0.0
Summary: Modulo ponte tra emissione fatture elettroniche e imposta di bollo
Home-page: https://github.com/OCA/l10n-italy
Author: Agile Business Group, Odoo Community Association (OCA)
Author-email: support@odoo-community.org
License: LGPL-3
Platform: UNKNOWN
Classifier: Programming Language :: Python
Classifier: Framework :: Odoo
Classifier: License :: OSI Approved :: GNU Lesser General Public License v3 (LGPLv3)
Classifier: Development Status :: 4 - Beta
Requires-Python: ~=2.7
Requires-Dist: odoo10-addon-l10n-it-account-stamp
Requires-Dist: odoo10-addon-l10n-it-fatturapa-out
Requires-Dist: odoo (<10.1dev,>=10.0)
